{
  "id": "yu5k9",
  "num": "15",
  "sequence": "",
  "tier": "Policy & People",
  "category": "paper",
  "title": "Measuring Failure and Success",
  "subtitle": "How we judge what works and what does not.",
  "track": "Human and Change Management",
  "authors": [
    "Ministry of Technology and Innovation"
  ],
  "published": null,
  "reading_min": null,
  "status": "Draft",
  "tags": [],
  "repo": null,
  "abstract": "Forthcoming. This paper sits in the Human and Change Management group of the collection. The body will be written from source materials.",
  "translation_status": "untranslated",
  "hero_image": {
    "src": "public/images/yu5k9/fr/hero.jpg",
    "alt": "Editorial image for: Measuring Failure and Success",
    "image_prompt": "An editorial cover image for the whitepaper titled \"Measuring Failure and Success\". Muted Alberta cream palette with navy and rust accents. Archival print quality, no text, no logos.",
    "style_kind": "cover"
  },
  "audio": {
    "src": "public/audio/fr/yu5k9.mp3"
  },
  "tldr_presentation": {
    "id": "yu5k9-tldr",
    "title": "The paper, in brief",
    "locale": "fr",
    "owner_id": "yu5k9",
    "slides": [
      {
        "id": "01",
        "title": "Measuring Failure and Success",
        "audio_file": "public/audio/fr/yu5k9-tldr/01.mp3",
        "visual": "title",
        "caption": "Human and Change Management",
        "subcaption": "",
        "text": "Measuring Failure and Success. Content forthcoming."
      }
    ]
  },
  "embedded_presentations": [],
  "sections": [
    {
      "n": "01",
      "title": "Overview"
    }
  ],
  "blocks": [
    {
      "type": "section_heading",
      "n": "01",
      "title": "Overview"
    },
    {
      "type": "paragraph",
      "text": "<strong>Content forthcoming.</strong> The structure is in place. The body will be written from source materials, not auto-generated."
    }
  ],
  "_meta": {
    "placeholder": true,
    "written_by": "structural-stub"
  },
  "related": []
}
